<?xml version="1.0" encoding="UTF-8"?>
<library>
  <groups>
    <group name="グループ名" expanded="false"/>
    <group name="サンプル・グループ" expanded="false"/>
  </groups>
  <sets>
    <set name="サンプル・セット">
      <font>C:\WINDOWS\Fonts\font_1_honokamin.ttf</font>
      <font>C:\WINDOWS\Fonts\UtsukushiFONT.otf</font>
      <font>C:\WINDOWS\Fonts\07YasashisaAntique.otf</font>
      <font>C:\WINDOWS\Fonts\07やさしさゴシック.ttf</font>
      <font>C:\WINDOWS\Fonts\07やさしさゴシックボールド.ttf</font>
      <font>C:\WINDOWS\Fonts\ロゴたいぷゴシック.otf</font>
      <font>C:\WINDOWS\Fonts\ロゴたいぷゴシックCondense.otf</font>
      <font>C:\WINDOWS\Fonts\Adamas-Regular.otf</font>
      <font>C:\WINDOWS\Fonts\arial.ttf</font>
      <font>C:\WINDOWS\Fonts\ariblk.ttf</font>
      <font>C:\WINDOWS\Fonts\arialbd.ttf</font>
      <font>C:\WINDOWS\Fonts\arialbi.ttf</font>
      <font>C:\WINDOWS\Fonts\ariali.ttf</font>
      <font>C:\WINDOWS\Fonts\BispoOriginal.otf</font>
      <font>C:\WINDOWS\Fonts\Bokutoh99-UH.ttf</font>
      <font>C:\WINDOWS\Fonts\Bokutoh99-UK.ttf</font>
      <font>C:\WINDOWS\Fonts\BokutohKuzure-UH.ttf</font>
      <font>C:\WINDOWS\Fonts\BokutohKuzure-UK.ttf</font>
      <font>C:\WINDOWS\Fonts\calibri.ttf</font>
      <font>C:\WINDOWS\Fonts\calibrib.ttf</font>
      <font>C:\WINDOWS\Fonts\calibriz.ttf</font>
      <font>C:\WINDOWS\Fonts\calibrii.ttf</font>
      <font>C:\WINDOWS\Fonts\calibril.ttf</font>
      <font>C:\WINDOWS\Fonts\calibrili.ttf</font>
      <font>C:\WINDOWS\Fonts\cambria.ttc</font>
      <font>C:\WINDOWS\Fonts\cambriab.ttf</font>
      <font>C:\WINDOWS\Fonts\cambriaz.ttf</font>
      <font>C:\WINDOWS\Fonts\cambriai.ttf</font>
      <font>C:\WINDOWS\Fonts\candara.ttf</font>
      <font>C:\WINDOWS\Fonts\candarab.ttf</font>
      <font>C:\WINDOWS\Fonts\candaraz.ttf</font>
      <font>C:\WINDOWS\Fonts\candarai.ttf</font>
      <font>C:\WINDOWS\Fonts\COM4F_RG.TTF</font>
      <font>C:\WINDOWS\Fonts\comic.ttf</font>
      <font>C:\WINDOWS\Fonts\comicbd.ttf</font>
      <font>C:\WINDOWS\Fonts\comicz.ttf</font>
      <font>C:\WINDOWS\Fonts\comici.ttf</font>
      <font>C:\WINDOWS\Fonts\consola.ttf</font>
      <font>C:\WINDOWS\Fonts\consolab.ttf</font>
      <font>C:\WINDOWS\Fonts\consolaz.ttf</font>
      <font>C:\WINDOWS\Fonts\consolai.ttf</font>
      <font>C:\WINDOWS\Fonts\constan.ttf</font>
      <font>C:\WINDOWS\Fonts\constanb.ttf</font>
      <font>C:\WINDOWS\Fonts\constanz.ttf</font>
      <font>C:\WINDOWS\Fonts\constani.ttf</font>
      <font>C:\WINDOWS\Fonts\corbel.ttf</font>
      <font>C:\WINDOWS\Fonts\corbelb.ttf</font>
      <font>C:\WINDOWS\Fonts\corbelz.ttf</font>
      <font>C:\WINDOWS\Fonts\corbeli.ttf</font>
      <font>C:\WINDOWS\Fonts\cour.ttf</font>
      <font>C:\WINDOWS\Fonts\courbd.ttf</font>
      <font>C:\WINDOWS\Fonts\courbi.ttf</font>
      <font>C:\WINDOWS\Fonts\couri.ttf</font>
      <font>C:\WINDOWS\Fonts\dejima-mincho-r227.ttf</font>
      <font>C:\WINDOWS\Fonts\ebrima.ttf</font>
      <font>C:\WINDOWS\Fonts\ebrimabd.ttf</font>
      <font>C:\WINDOWS\Fonts\f910-shin-comic-2.01.otf</font>
      <font>C:\WINDOWS\Fonts\ferrica.ttf</font>
      <font>C:\WINDOWS\Fonts\framd.ttf</font>
      <font>C:\WINDOWS\Fonts\framdit.ttf</font>
      <font>C:\WINDOWS\Fonts\Gabriola.ttf</font>
      <font>C:\WINDOWS\Fonts\gadugi.ttf</font>
      <font>C:\WINDOWS\Fonts\gadugib.ttf</font>
      <font>C:\WINDOWS\Fonts\georgia.ttf</font>
      <font>C:\WINDOWS\Fonts\georgiab.ttf</font>
      <font>C:\WINDOWS\Fonts\georgiaz.ttf</font>
      <font>C:\WINDOWS\Fonts\georgiai.ttf</font>
      <font>C:\WINDOWS\Fonts\Hagin Caps Medium.otf</font>
      <font>C:\WINDOWS\Fonts\Hagin Caps Thin.otf</font>
      <font>C:\WINDOWS\Fonts\Hexa.otf</font>
      <font>C:\WINDOWS\Fonts\HPSimplified_Rg.ttf</font>
      <font>C:\WINDOWS\Fonts\HPSimplified_Bd.ttf</font>
      <font>C:\WINDOWS\Fonts\HPSimplified_BdIt.ttf</font>
      <font>C:\WINDOWS\Fonts\HPSimplified_It.ttf</font>
      <font>C:\WINDOWS\Fonts\HPSimplified_Lt.ttf</font>
      <font>C:\WINDOWS\Fonts\HPSimplified_LtIt.ttf</font>
      <font>C:\WINDOWS\Fonts\HYPED_Font.otf</font>
      <font>C:\WINDOWS\Fonts\impact.ttf</font>
      <font>C:\WINDOWS\Fonts\ipaexg.ttf</font>
      <font>C:\WINDOWS\Fonts\ipaexm.ttf</font>
      <font>C:\WINDOWS\Fonts\ipag.ttf</font>
      <font>C:\WINDOWS\Fonts\JapanSans100.otf</font>
      <font>C:\WINDOWS\Fonts\JapanSans70.ttf</font>
      <font>C:\WINDOWS\Fonts\JapanSans70_0.otf</font>
      <font>C:\WINDOWS\Fonts\JapanSans80.otf</font>
      <font>C:\WINDOWS\Fonts\JapanSans80_0.otf</font>
      <font>C:\WINDOWS\Fonts\JapanSans90.otf</font>
      <font>C:\WINDOWS\Fonts\JapanSans90_0.otf</font>
      <font>C:\WINDOWS\Fonts\javatext.ttf</font>
      <font>C:\WINDOWS\Fonts\Koruri-Bold.ttf</font>
      <font>C:\WINDOWS\Fonts\Koruri-Extrabold.ttf</font>
      <font>C:\WINDOWS\Fonts\Koruri-Light.ttf</font>
      <font>C:\WINDOWS\Fonts\Koruri-Regular.ttf</font>
      <font>C:\WINDOWS\Fonts\Koruri-Semibold.ttf</font>
      <font>C:\WINDOWS\Fonts\leelawui.ttf</font>
      <font>C:\WINDOWS\Fonts\leelauib.ttf</font>
      <font>C:\WINDOWS\Fonts\leeluisl.ttf</font>
      <font>C:\WINDOWS\Fonts\lucon.TTF</font>
      <font>C:\WINDOWS\Fonts\l_10646.ttf</font>
      <font>C:\WINDOWS\Fonts\MagicRing.ttf</font>
      <font>C:\WINDOWS\Fonts\malgun.ttf</font>
      <font>C:\WINDOWS\Fonts\malgunbd.ttf</font>
      <font>C:\WINDOWS\Fonts\malgunsl.ttf</font>
      <font>C:\WINDOWS\Fonts\meiryo.ttc</font>
      <font>C:\WINDOWS\Fonts\meiryob.ttc</font>
      <font>C:\WINDOWS\Fonts\mgenplus-1c-black.ttf</font>
      <font>C:\WINDOWS\Fonts\mgenplus-1c-bold.ttf</font>
      <font>C:\WINDOWS\Fonts\mgenplus-1c-heavy.ttf</font>
      <font>C:\WINDOWS\Fonts\mgenplus-1c-light.ttf</font>
      <font>C:\WINDOWS\Fonts\mgenplus-1c-medium.ttf</font>
      <font>C:\WINDOWS\Fonts\mgenplus-1c-regular.ttf</font>
      <font>C:\WINDOWS\Fonts\mgenplus-1c-thin.ttf</font>
      <font>C:\WINDOWS\Fonts\mgenplus-1cp-black.ttf</font>
      <font>C:\WINDOWS\Fonts\mgenplus-1cp-bold.ttf</font>
      <font>C:\WINDOWS\Fonts\mgenplus-1cp-heavy.ttf</font>
      <font>C:\WINDOWS\Fonts\mgenplus-1cp-light.ttf</font>
      <font>C:\WINDOWS\Fonts\mgenplus-1cp-medium.ttf</font>
      <font>C:\WINDOWS\Fonts\mgenplus-1cp-regular.ttf</font>
      <font>C:\WINDOWS\Fonts\mgenplus-1cp-thin.ttf</font>
      <font>C:\WINDOWS\Fonts\mgenplus-1m-bold.ttf</font>
      <font>C:\WINDOWS\Fonts\mgenplus-1m-light.ttf</font>
      <font>C:\WINDOWS\Fonts\mgenplus-1m-medium.ttf</font>
      <font>C:\WINDOWS\Fonts\mgenplus-1m-regular.ttf</font>
      <font>C:\WINDOWS\Fonts\mgenplus-1m-thin.ttf</font>
      <font>C:\WINDOWS\Fonts\mgenplus-1mn-bold.ttf</font>
      <font>C:\WINDOWS\Fonts\mgenplus-1mn-light.ttf</font>
      <font>C:\WINDOWS\Fonts\mgenplus-1mn-medium.ttf</font>
      <font>C:\WINDOWS\Fonts\mgenplus-1mn-regular.ttf</font>
      <font>C:\WINDOWS\Fonts\mgenplus-1mn-thin.ttf</font>
      <font>C:\WINDOWS\Fonts\mgenplus-1p-black.ttf</font>
      <font>C:\WINDOWS\Fonts\mgenplus-1p-bold.ttf</font>
      <font>C:\WINDOWS\Fonts\mgenplus-1p-heavy.ttf</font>
      <font>C:\WINDOWS\Fonts\mgenplus-1p-light.ttf</font>
      <font>C:\WINDOWS\Fonts\mgenplus-1p-medium.ttf</font>
      <font>C:\WINDOWS\Fonts\mgenplus-1p-regular.ttf</font>
      <font>C:\WINDOWS\Fonts\mgenplus-1p-thin.ttf</font>
      <font>C:\WINDOWS\Fonts\mgenplus-1pp-black.ttf</font>
      <font>C:\WINDOWS\Fonts\mgenplus-1pp-bold.ttf</font>
      <font>C:\WINDOWS\Fonts\mgenplus-1pp-heavy.ttf</font>
      <font>C:\WINDOWS\Fonts\mgenplus-1pp-light.ttf</font>
      <font>C:\WINDOWS\Fonts\mgenplus-1pp-medium.ttf</font>
      <font>C:\WINDOWS\Fonts\mgenplus-1pp-regular.ttf</font>
      <font>C:\WINDOWS\Fonts\mgenplus-1pp-thin.ttf</font>
      <font>C:\WINDOWS\Fonts\mgenplus-2c-black.ttf</font>
      <font>C:\WINDOWS\Fonts\mgenplus-2c-bold.ttf</font>
      <font>C:\WINDOWS\Fonts\mgenplus-2c-heavy.ttf</font>
      <font>C:\WINDOWS\Fonts\mgenplus-2c-light.ttf</font>
      <font>C:\WINDOWS\Fonts\mgenplus-2c-medium.ttf</font>
      <font>C:\WINDOWS\Fonts\mgenplus-2c-regular.ttf</font>
      <font>C:\WINDOWS\Fonts\mgenplus-2c-thin.ttf</font>
      <font>C:\WINDOWS\Fonts\mgenplus-2cp-black.ttf</font>
      <font>C:\WINDOWS\Fonts\mgenplus-2cp-bold.ttf</font>
      <font>C:\WINDOWS\Fonts\mgenplus-2cp-heavy.ttf</font>
      <font>C:\WINDOWS\Fonts\mgenplus-2cp-light.ttf</font>
      <font>C:\WINDOWS\Fonts\mgenplus-2cp-medium.ttf</font>
      <font>C:\WINDOWS\Fonts\mgenplus-2cp-regular.ttf</font>
      <font>C:\WINDOWS\Fonts\mgenplus-2cp-thin.ttf</font>
      <font>C:\WINDOWS\Fonts\mgenplus-2m-bold.ttf</font>
      <font>C:\WINDOWS\Fonts\mgenplus-2m-light.ttf</font>
      <font>C:\WINDOWS\Fonts\mgenplus-2m-medium.ttf</font>
      <font>C:\WINDOWS\Fonts\mgenplus-2m-regular.ttf</font>
      <font>C:\WINDOWS\Fonts\mgenplus-2m-thin.ttf</font>
      <font>C:\WINDOWS\Fonts\mgenplus-2p-black.ttf</font>
      <font>C:\WINDOWS\Fonts\mgenplus-2p-bold.ttf</font>
      <font>C:\WINDOWS\Fonts\mgenplus-2p-heavy.ttf</font>
      <font>C:\WINDOWS\Fonts\mgenplus-2p-light.ttf</font>
      <font>C:\WINDOWS\Fonts\mgenplus-2p-medium.ttf</font>
      <font>C:\WINDOWS\Fonts\mgenplus-2p-regular.ttf</font>
      <font>C:\WINDOWS\Fonts\mgenplus-2p-thin.ttf</font>
      <font>C:\WINDOWS\Fonts\mgenplus-2pp-black.ttf</font>
      <font>C:\WINDOWS\Fonts\mgenplus-2pp-bold.ttf</font>
      <font>C:\WINDOWS\Fonts\mgenplus-2pp-heavy.ttf</font>
      <font>C:\WINDOWS\Fonts\mgenplus-2pp-light.ttf</font>
      <font>C:\WINDOWS\Fonts\mgenplus-2pp-medium.ttf</font>
      <font>C:\WINDOWS\Fonts\mgenplus-2pp-regular.ttf</font>
      <font>C:\WINDOWS\Fonts\mgenplus-2pp-thin.ttf</font>
      <font>C:\WINDOWS\Fonts\himalaya.ttf</font>
      <font>C:\WINDOWS\Fonts\msjh.ttc</font>
      <font>C:\WINDOWS\Fonts\msjhbd.ttc</font>
      <font>C:\WINDOWS\Fonts\msjhl.ttc</font>
      <font>C:\WINDOWS\Fonts\ntailu.ttf</font>
      <font>C:\WINDOWS\Fonts\ntailub.ttf</font>
      <font>C:\WINDOWS\Fonts\phagspa.ttf</font>
      <font>C:\WINDOWS\Fonts\phagspab.ttf</font>
      <font>C:\WINDOWS\Fonts\micross.ttf</font>
      <font>C:\WINDOWS\Fonts\taile.ttf</font>
      <font>C:\WINDOWS\Fonts\taileb.ttf</font>
      <font>C:\WINDOWS\Fonts\msyh.ttc</font>
      <font>C:\WINDOWS\Fonts\msyhbd.ttc</font>
      <font>C:\WINDOWS\Fonts\msyhl.ttc</font>
      <font>C:\WINDOWS\Fonts\msyi.ttf</font>
      <font>C:\WINDOWS\Fonts\mingliub.ttc</font>
      <font>C:\WINDOWS\Fonts\mini-wakuwaku.otf</font>
      <font>C:\WINDOWS\Fonts\mini-wakuwaku-maru.otf</font>
      <font>C:\WINDOWS\Fonts\monbaiti.ttf</font>
      <font>C:\WINDOWS\Fonts\msgothic.ttc</font>
      <font>C:\WINDOWS\Fonts\msmincho.ttc</font>
      <font>C:\WINDOWS\Fonts\mvboli.ttf</font>
      <font>C:\WINDOWS\Fonts\mmrtext.ttf</font>
      <font>C:\WINDOWS\Fonts\mmrtextb.ttf</font>
      <font>C:\WINDOWS\Fonts\yuminl.ttf</font>
      <font>C:\WINDOWS\Fonts\yumindb.ttf</font>
      <font>C:\WINDOWS\Fonts\yumin.ttf</font>
      <font>C:\WINDOWS\Fonts\Nirmala.ttf</font>
      <font>C:\WINDOWS\Fonts\NirmalaB.ttf</font>
      <font>C:\WINDOWS\Fonts\NirmalaS.ttf</font>
      <font>C:\WINDOWS\Fonts\NotoEmoji-Regular.ttf</font>
      <font>C:\WINDOWS\Fonts\NotoKufiArabic-Regular.ttf</font>
      <font>C:\WINDOWS\Fonts\NotoKufiArabic-Bold.ttf</font>
      <font>C:\WINDOWS\Fonts\NotoNaskhArabic-Regular.ttf</font>
      <font>C:\WINDOWS\Fonts\NotoNaskhArabic-Bold.ttf</font>
      <font>C:\WINDOWS\Fonts\NotoNastaliqUrdu-Regular.ttf</font>
      <font>C:\WINDOWS\Fonts\NotoSans-Regular.ttf</font>
      <font>C:\WINDOWS\Fonts\NotoSansArmenian-Regular.ttf</font>
      <font>C:\WINDOWS\Fonts\NotoSansArmenian-Bold.ttf</font>
      <font>C:\WINDOWS\Fonts\NotoSansAvestan-Regular.ttf</font>
      <font>C:\WINDOWS\Fonts\NotoSansBalinese-Regular.ttf</font>
      <font>C:\WINDOWS\Fonts\NotoSansBamum-Regular.ttf</font>
      <font>C:\WINDOWS\Fonts\NotoSansBatak-Regular.ttf</font>
      <font>C:\WINDOWS\Fonts\NotoSansBengali-Regular.ttf</font>
      <font>C:\WINDOWS\Fonts\NotoSansBengali-Bold.ttf</font>
      <font>C:\WINDOWS\Fonts\NotoSans-Bold.ttf</font>
      <font>C:\WINDOWS\Fonts\NotoSans-BoldItalic.ttf</font>
      <font>C:\WINDOWS\Fonts\NotoSansBrahmi-Regular.ttf</font>
      <font>C:\WINDOWS\Fonts\NotoSansBuginese-Regular.ttf</font>
      <font>C:\WINDOWS\Fonts\NotoSansBuhid-Regular.ttf</font>
      <font>C:\WINDOWS\Fonts\NotoSansCanadianAboriginal-Regular.ttf</font>
      <font>C:\WINDOWS\Fonts\NotoSansCarian-Regular.ttf</font>
      <font>C:\WINDOWS\Fonts\NotoSansCham-Regular.ttf</font>
      <font>C:\WINDOWS\Fonts\NotoSansCham-Bold.ttf</font>
      <font>C:\WINDOWS\Fonts\NotoSansCherokee-Regular.ttf</font>
      <font>C:\WINDOWS\Fonts\NotoSansCJKjp-Black.otf</font>
      <font>C:\WINDOWS\Fonts\NotoSansCJKjp-Bold.otf</font>
      <font>C:\WINDOWS\Fonts\NotoSansCJKjp-DemiLight.otf</font>
      <font>C:\WINDOWS\Fonts\NotoSansCJKjp-Light.otf</font>
      <font>C:\WINDOWS\Fonts\NotoSansCJKjp-Medium.otf</font>
      <font>C:\WINDOWS\Fonts\NotoSansCJKjp-Regular.otf</font>
      <font>C:\WINDOWS\Fonts\NotoSansCJKjp-Thin.otf</font>
      <font>C:\WINDOWS\Fonts\NotoSansCJKkr-Black.otf</font>
      <font>C:\WINDOWS\Fonts\NotoSansCJKkr-Bold.otf</font>
      <font>C:\WINDOWS\Fonts\NotoSansCJKkr-DemiLight.otf</font>
      <font>C:\WINDOWS\Fonts\NotoSansCJKkr-Light.otf</font>
      <font>C:\WINDOWS\Fonts\NotoSansCJKkr-Medium.otf</font>
      <font>C:\WINDOWS\Fonts\NotoSansCJKkr-Regular.otf</font>
      <font>C:\WINDOWS\Fonts\NotoSansCJKkr-Thin.otf</font>
      <font>C:\WINDOWS\Fonts\NotoSansCJKsc-Black.otf</font>
      <font>C:\WINDOWS\Fonts\NotoSansCJKsc-Bold.otf</font>
      <font>C:\WINDOWS\Fonts\NotoSansCJKsc-DemiLight.otf</font>
      <font>C:\WINDOWS\Fonts\NotoSansCJKsc-Light.otf</font>
      <font>C:\WINDOWS\Fonts\NotoSansCJKsc-Medium.otf</font>
      <font>C:\WINDOWS\Fonts\NotoSansCJKsc-Regular.otf</font>
      <font>C:\WINDOWS\Fonts\NotoSansCJKsc-Thin.otf</font>
      <font>C:\WINDOWS\Fonts\NotoSansCJKtc-Black.otf</font>
      <font>C:\WINDOWS\Fonts\NotoSansCJKtc-Bold.otf</font>
      <font>C:\WINDOWS\Fonts\NotoSansCJKtc-DemiLight.otf</font>
      <font>C:\WINDOWS\Fonts\NotoSansCJKtc-Light.otf</font>
      <font>C:\WINDOWS\Fonts\NotoSansCJKtc-Medium.otf</font>
      <font>C:\WINDOWS\Fonts\NotoSansCJKtc-Regular.otf</font>
      <font>C:\WINDOWS\Fonts\NotoSansCJKtc-Thin.otf</font>
      <font>C:\WINDOWS\Fonts\NotoSansCoptic-Regular.ttf</font>
      <font>C:\WINDOWS\Fonts\NotoSansCuneiform-Regular.ttf</font>
      <font>C:\WINDOWS\Fonts\NotoSansCypriot-Regular.ttf</font>
      <font>C:\WINDOWS\Fonts\NotoSansDeseret-Regular.ttf</font>
      <font>C:\WINDOWS\Fonts\NotoSansDevanagari-Regular.ttf</font>
      <font>C:\WINDOWS\Fonts\NotoSansDevanagari-Bold.ttf</font>
      <font>C:\WINDOWS\Fonts\NotoSansEgyptianHieroglyphs-Regular.ttf</font>
      <font>C:\WINDOWS\Fonts\NotoSansEthiopic-Regular.ttf</font>
      <font>C:\WINDOWS\Fonts\NotoSansEthiopic-Bold.ttf</font>
      <font>C:\WINDOWS\Fonts\NotoSansGeorgian-Regular.ttf</font>
      <font>C:\WINDOWS\Fonts\NotoSansGeorgian-Bold.ttf</font>
      <font>C:\WINDOWS\Fonts\NotoSansGlagolitic-Regular.ttf</font>
      <font>C:\WINDOWS\Fonts\NotoSansGothic-Regular.ttf</font>
      <font>C:\WINDOWS\Fonts\NotoSansGujarati-Regular.ttf</font>
      <font>C:\WINDOWS\Fonts\NotoSansGujarati-Bold.ttf</font>
      <font>C:\WINDOWS\Fonts\NotoSansGurmukhi-Regular.ttf</font>
      <font>C:\WINDOWS\Fonts\NotoSansGurmukhi-Bold.ttf</font>
      <font>C:\WINDOWS\Fonts\NotoSansHanunoo-Regular.ttf</font>
      <font>C:\WINDOWS\Fonts\NotoSansHebrew-Regular.ttf</font>
      <font>C:\WINDOWS\Fonts\NotoSansHebrew-Bold.ttf</font>
      <font>C:\WINDOWS\Fonts\NotoSansImperialAramaic-Regular.ttf</font>
      <font>C:\WINDOWS\Fonts\NotoSansInscriptionalPahlavi-Regular.ttf</font>
      <font>C:\WINDOWS\Fonts\NotoSansInscriptionalParthian-Regular.ttf</font>
      <font>C:\WINDOWS\Fonts\NotoSans-Italic.ttf</font>
      <font>C:\WINDOWS\Fonts\NotoSansJavanese-Regular.ttf</font>
      <font>C:\WINDOWS\Fonts\NotoSansKaithi-Regular.ttf</font>
      <font>C:\WINDOWS\Fonts\NotoSansKannada-Regular.ttf</font>
      <font>C:\WINDOWS\Fonts\NotoSansKannada-Bold.ttf</font>
      <font>C:\WINDOWS\Fonts\NotoSansKayahLi-Regular.ttf</font>
      <font>C:\WINDOWS\Fonts\NotoSansKharoshthi-Regular.ttf</font>
      <font>C:\WINDOWS\Fonts\NotoSansKhmer-Regular.ttf</font>
      <font>C:\WINDOWS\Fonts\NotoSansKhmer-Bold.ttf</font>
      <font>C:\WINDOWS\Fonts\NotoSansLao-Regular.ttf</font>
      <font>C:\WINDOWS\Fonts\NotoSansLao-Bold.ttf</font>
      <font>C:\WINDOWS\Fonts\NotoSansLepcha-Regular.ttf</font>
      <font>C:\WINDOWS\Fonts\NotoSansLimbu-Regular.ttf</font>
      <font>C:\WINDOWS\Fonts\NotoSansLinearB-Regular.ttf</font>
      <font>C:\WINDOWS\Fonts\NotoSansLisu-Regular.ttf</font>
      <font>C:\WINDOWS\Fonts\NotoSansLycian-Regular.ttf</font>
      <font>C:\WINDOWS\Fonts\NotoSansLydian-Regular.ttf</font>
      <font>C:\WINDOWS\Fonts\NotoSansMalayalam-Regular.ttf</font>
      <font>C:\WINDOWS\Fonts\NotoSansMalayalam-Bold.ttf</font>
      <font>C:\WINDOWS\Fonts\NotoSansMandaic-Regular.ttf</font>
      <font>C:\WINDOWS\Fonts\NotoSansMeeteiMayek-Regular.ttf</font>
      <font>C:\WINDOWS\Fonts\NotoSansMongolian-Regular.ttf</font>
      <font>C:\WINDOWS\Fonts\NotoSansMonoCJKjp-Bold.otf</font>
      <font>C:\WINDOWS\Fonts\NotoSansMonoCJKjp-Regular.otf</font>
      <font>C:\WINDOWS\Fonts\NotoSansMonoCJKkr-Bold.otf</font>
      <font>C:\WINDOWS\Fonts\NotoSansMonoCJKkr-Regular.otf</font>
      <font>C:\WINDOWS\Fonts\NotoSansMonoCJKsc-Bold.otf</font>
      <font>C:\WINDOWS\Fonts\NotoSansMonoCJKsc-Regular.otf</font>
      <font>C:\WINDOWS\Fonts\NotoSansMonoCJKtc-Bold.otf</font>
      <font>C:\WINDOWS\Fonts\NotoSansMonoCJKtc-Regular.otf</font>
      <font>C:\WINDOWS\Fonts\NotoSansMyanmar-Regular.ttf</font>
      <font>C:\WINDOWS\Fonts\NotoSansMyanmar-Bold.ttf</font>
      <font>C:\WINDOWS\Fonts\NotoSansNewTaiLue-Regular.ttf</font>
      <font>C:\WINDOWS\Fonts\NotoSansNKo-Regular.ttf</font>
      <font>C:\WINDOWS\Fonts\NotoSansOgham-Regular.ttf</font>
      <font>C:\WINDOWS\Fonts\NotoSansOlChiki-Regular.ttf</font>
      <font>C:\WINDOWS\Fonts\NotoSansOldItalic-Regular.ttf</font>
      <font>C:\WINDOWS\Fonts\NotoSansOldPersian-Regular.ttf</font>
      <font>C:\WINDOWS\Fonts\NotoSansOldSouthArabian-Regular.ttf</font>
      <font>C:\WINDOWS\Fonts\NotoSansOldTurkic-Regular.ttf</font>
      <font>C:\WINDOWS\Fonts\NotoSansOriya-Regular.ttf</font>
      <font>C:\WINDOWS\Fonts\NotoSansOriya-Bold.ttf</font>
      <font>C:\WINDOWS\Fonts\NotoSansOsmanya-Regular.ttf</font>
      <font>C:\WINDOWS\Fonts\NotoSansPhagsPa-Regular.ttf</font>
      <font>C:\WINDOWS\Fonts\NotoSansPhoenician-Regular.ttf</font>
      <font>C:\WINDOWS\Fonts\NotoSansRejang-Regular.ttf</font>
      <font>C:\WINDOWS\Fonts\NotoSansRunic-Regular.ttf</font>
      <font>C:\WINDOWS\Fonts\NotoSansSamaritan-Regular.ttf</font>
      <font>C:\WINDOWS\Fonts\NotoSansSaurashtra-Regular.ttf</font>
      <font>C:\WINDOWS\Fonts\NotoSansShavian-Regular.ttf</font>
      <font>C:\WINDOWS\Fonts\NotoSansSinhala-Regular.ttf</font>
      <font>C:\WINDOWS\Fonts\NotoSansSinhala-Bold.ttf</font>
      <font>C:\WINDOWS\Fonts\NotoSansSundanese-Regular.ttf</font>
      <font>C:\WINDOWS\Fonts\NotoSansSylotiNagri-Regular.ttf</font>
      <font>C:\WINDOWS\Fonts\NotoSansSymbols-Regular.ttf</font>
      <font>C:\WINDOWS\Fonts\NotoSansSyriacEastern-Regular.ttf</font>
      <font>C:\WINDOWS\Fonts\NotoSansSyriacEstrangela-Regular.ttf</font>
      <font>C:\WINDOWS\Fonts\NotoSansSyriacWestern-Regular.ttf</font>
      <font>C:\WINDOWS\Fonts\NotoSansTagalog-Regular.ttf</font>
      <font>C:\WINDOWS\Fonts\NotoSansTagbanwa-Regular.ttf</font>
      <font>C:\WINDOWS\Fonts\NotoSansTaiLe-Regular.ttf</font>
      <font>C:\WINDOWS\Fonts\NotoSansTaiTham-Regular.ttf</font>
      <font>C:\WINDOWS\Fonts\NotoSansTaiViet-Regular.ttf</font>
      <font>C:\WINDOWS\Fonts\NotoSansTamil-Regular.ttf</font>
      <font>C:\WINDOWS\Fonts\NotoSansTamil-Bold.ttf</font>
      <font>C:\WINDOWS\Fonts\NotoSansTelugu-Regular.ttf</font>
      <font>C:\WINDOWS\Fonts\NotoSansTelugu-Bold.ttf</font>
      <font>C:\WINDOWS\Fonts\NotoSansThaana-Regular.ttf</font>
      <font>C:\WINDOWS\Fonts\NotoSansThaana-Bold.ttf</font>
      <font>C:\WINDOWS\Fonts\NotoSansThai-Regular.ttf</font>
      <font>C:\WINDOWS\Fonts\NotoSansThai-Bold.ttf</font>
      <font>C:\WINDOWS\Fonts\NotoSansTibetan-Regular.ttf</font>
      <font>C:\WINDOWS\Fonts\NotoSansTibetan-Bold.ttf</font>
      <font>C:\WINDOWS\Fonts\NotoSansTifinagh-Regular.ttf</font>
      <font>C:\WINDOWS\Fonts\NotoSansUgaritic-Regular.ttf</font>
      <font>C:\WINDOWS\Fonts\NotoSansVai-Regular.ttf</font>
      <font>C:\WINDOWS\Fonts\NotoSansYi-Regular.ttf</font>
      <font>C:\WINDOWS\Fonts\NotoSerif-Regular.ttf</font>
      <font>C:\WINDOWS\Fonts\NotoSerifArmenian-Regular.ttf</font>
      <font>C:\WINDOWS\Fonts\NotoSerifArmenian-Bold.ttf</font>
      <font>C:\WINDOWS\Fonts\NotoSerif-Bold.ttf</font>
      <font>C:\WINDOWS\Fonts\NotoSerif-BoldItalic.ttf</font>
      <font>C:\WINDOWS\Fonts\NotoSerifGeorgian-Regular.ttf</font>
      <font>C:\WINDOWS\Fonts\NotoSerifGeorgian-Bold.ttf</font>
      <font>C:\WINDOWS\Fonts\NotoSerif-Italic.ttf</font>
      <font>C:\WINDOWS\Fonts\NotoSerifKhmer-Regular.ttf</font>
      <font>C:\WINDOWS\Fonts\NotoSerifKhmer-Bold.ttf</font>
      <font>C:\WINDOWS\Fonts\NotoSerifLao-Regular.ttf</font>
      <font>C:\WINDOWS\Fonts\NotoSerifLao-Bold.ttf</font>
      <font>C:\WINDOWS\Fonts\NotoSerifThai-Regular.ttf</font>
      <font>C:\WINDOWS\Fonts\NotoSerifThai-Bold.ttf</font>
      <font>C:\WINDOWS\Fonts\simsun.ttc</font>
      <font>C:\WINDOWS\Fonts\opium_roadie.ttf</font>
      <font>C:\WINDOWS\Fonts\Origram.otf</font>
      <font>C:\WINDOWS\Fonts\pala.ttf</font>
      <font>C:\WINDOWS\Fonts\palab.ttf</font>
      <font>C:\WINDOWS\Fonts\palabi.ttf</font>
      <font>C:\WINDOWS\Fonts\palai.ttf</font>
      <font>C:\WINDOWS\Fonts\PlayfairDisplay-Regular.ttf</font>
      <font>C:\WINDOWS\Fonts\PlayfairDisplay-Black.ttf</font>
      <font>C:\WINDOWS\Fonts\PlayfairDisplay-BlackItalic.ttf</font>
      <font>C:\WINDOWS\Fonts\PlayfairDisplay-Bold.ttf</font>
      <font>C:\WINDOWS\Fonts\PlayfairDisplay-BoldItalic.ttf</font>
      <font>C:\WINDOWS\Fonts\PlayfairDisplay-Italic.ttf</font>
      <font>C:\WINDOWS\Fonts\font_1_kokumr_1.00_rls.ttf</font>
      <font>C:\WINDOWS\Fonts\Rex Bold.otf</font>
      <font>C:\WINDOWS\Fonts\Rex Bold Inline.otf</font>
      <font>C:\WINDOWS\Fonts\Rex Light.otf</font>
      <font>C:\WINDOWS\Fonts\rounded-mgenplus-1c-black.ttf</font>
      <font>C:\WINDOWS\Fonts\rounded-mgenplus-1c-bold.ttf</font>
      <font>C:\WINDOWS\Fonts\rounded-mgenplus-1c-heavy.ttf</font>
      <font>C:\WINDOWS\Fonts\rounded-mgenplus-1c-light.ttf</font>
      <font>C:\WINDOWS\Fonts\rounded-mgenplus-1c-medium.ttf</font>
      <font>C:\WINDOWS\Fonts\rounded-mgenplus-1c-regular.ttf</font>
      <font>C:\WINDOWS\Fonts\rounded-mgenplus-1c-thin.ttf</font>
      <font>C:\WINDOWS\Fonts\rounded-mgenplus-1cp-black.ttf</font>
      <font>C:\WINDOWS\Fonts\rounded-mgenplus-1cp-bold.ttf</font>
      <font>C:\WINDOWS\Fonts\rounded-mgenplus-1cp-heavy.ttf</font>
      <font>C:\WINDOWS\Fonts\rounded-mgenplus-1cp-light.ttf</font>
      <font>C:\WINDOWS\Fonts\rounded-mgenplus-1cp-medium.ttf</font>
      <font>C:\WINDOWS\Fonts\rounded-mgenplus-1cp-regular.ttf</font>
      <font>C:\WINDOWS\Fonts\rounded-mgenplus-1cp-thin.ttf</font>
      <font>C:\WINDOWS\Fonts\rounded-mgenplus-1m-bold.ttf</font>
      <font>C:\WINDOWS\Fonts\rounded-mgenplus-1m-light.ttf</font>
      <font>C:\WINDOWS\Fonts\rounded-mgenplus-1m-medium.ttf</font>
      <font>C:\WINDOWS\Fonts\rounded-mgenplus-1m-regular.ttf</font>
      <font>C:\WINDOWS\Fonts\rounded-mgenplus-1m-thin.ttf</font>
      <font>C:\WINDOWS\Fonts\rounded-mgenplus-1mn-bold.ttf</font>
      <font>C:\WINDOWS\Fonts\rounded-mgenplus-1mn-light.ttf</font>
      <font>C:\WINDOWS\Fonts\rounded-mgenplus-1mn-medium.ttf</font>
      <font>C:\WINDOWS\Fonts\rounded-mgenplus-1mn-regular.ttf</font>
      <font>C:\WINDOWS\Fonts\rounded-mgenplus-1mn-thin.ttf</font>
      <font>C:\WINDOWS\Fonts\rounded-mgenplus-1p-black.ttf</font>
      <font>C:\WINDOWS\Fonts\rounded-mgenplus-1p-bold.ttf</font>
      <font>C:\WINDOWS\Fonts\rounded-mgenplus-1p-heavy.ttf</font>
      <font>C:\WINDOWS\Fonts\rounded-mgenplus-1p-light.ttf</font>
      <font>C:\WINDOWS\Fonts\rounded-mgenplus-1p-medium.ttf</font>
      <font>C:\WINDOWS\Fonts\rounded-mgenplus-1p-regular.ttf</font>
      <font>C:\WINDOWS\Fonts\rounded-mgenplus-1p-thin.ttf</font>
      <font>C:\WINDOWS\Fonts\rounded-mgenplus-1pp-black.ttf</font>
      <font>C:\WINDOWS\Fonts\rounded-mgenplus-1pp-bold.ttf</font>
      <font>C:\WINDOWS\Fonts\rounded-mgenplus-1pp-heavy.ttf</font>
      <font>C:\WINDOWS\Fonts\rounded-mgenplus-1pp-light.ttf</font>
      <font>C:\WINDOWS\Fonts\rounded-mgenplus-1pp-medium.ttf</font>
      <font>C:\WINDOWS\Fonts\rounded-mgenplus-1pp-regular.ttf</font>
      <font>C:\WINDOWS\Fonts\rounded-mgenplus-1pp-thin.ttf</font>
      <font>C:\WINDOWS\Fonts\rounded-mgenplus-2c-black.ttf</font>
      <font>C:\WINDOWS\Fonts\rounded-mgenplus-2c-bold.ttf</font>
      <font>C:\WINDOWS\Fonts\rounded-mgenplus-2c-heavy.ttf</font>
      <font>C:\WINDOWS\Fonts\rounded-mgenplus-2c-light.ttf</font>
      <font>C:\WINDOWS\Fonts\rounded-mgenplus-2c-medium.ttf</font>
      <font>C:\WINDOWS\Fonts\rounded-mgenplus-2c-regular.ttf</font>
      <font>C:\WINDOWS\Fonts\rounded-mgenplus-2c-thin.ttf</font>
      <font>C:\WINDOWS\Fonts\rounded-mgenplus-2cp-black.ttf</font>
      <font>C:\WINDOWS\Fonts\rounded-mgenplus-2cp-bold.ttf</font>
      <font>C:\WINDOWS\Fonts\rounded-mgenplus-2cp-heavy.ttf</font>
      <font>C:\WINDOWS\Fonts\rounded-mgenplus-2cp-light.ttf</font>
      <font>C:\WINDOWS\Fonts\rounded-mgenplus-2cp-medium.ttf</font>
      <font>C:\WINDOWS\Fonts\rounded-mgenplus-2cp-regular.ttf</font>
      <font>C:\WINDOWS\Fonts\rounded-mgenplus-2cp-thin.ttf</font>
      <font>C:\WINDOWS\Fonts\rounded-mgenplus-2m-bold.ttf</font>
      <font>C:\WINDOWS\Fonts\rounded-mgenplus-2m-light.ttf</font>
      <font>C:\WINDOWS\Fonts\rounded-mgenplus-2m-medium.ttf</font>
      <font>C:\WINDOWS\Fonts\rounded-mgenplus-2m-regular.ttf</font>
      <font>C:\WINDOWS\Fonts\rounded-mgenplus-2m-thin.ttf</font>
      <font>C:\WINDOWS\Fonts\rounded-mgenplus-2p-black.ttf</font>
      <font>C:\WINDOWS\Fonts\rounded-mgenplus-2p-bold.ttf</font>
      <font>C:\WINDOWS\Fonts\rounded-mgenplus-2p-heavy.ttf</font>
      <font>C:\WINDOWS\Fonts\rounded-mgenplus-2p-light.ttf</font>
      <font>C:\WINDOWS\Fonts\rounded-mgenplus-2p-medium.ttf</font>
      <font>C:\WINDOWS\Fonts\rounded-mgenplus-2p-regular.ttf</font>
      <font>C:\WINDOWS\Fonts\rounded-mgenplus-2p-thin.ttf</font>
      <font>C:\WINDOWS\Fonts\rounded-mgenplus-2pp-black.ttf</font>
      <font>C:\WINDOWS\Fonts\rounded-mgenplus-2pp-bold.ttf</font>
      <font>C:\WINDOWS\Fonts\rounded-mgenplus-2pp-heavy.ttf</font>
      <font>C:\WINDOWS\Fonts\rounded-mgenplus-2pp-light.ttf</font>
      <font>C:\WINDOWS\Fonts\rounded-mgenplus-2pp-medium.ttf</font>
      <font>C:\WINDOWS\Fonts\rounded-mgenplus-2pp-regular.ttf</font>
      <font>C:\WINDOWS\Fonts\rounded-l-mgenplus-1c-black.ttf</font>
      <font>C:\WINDOWS\Fonts\rounded-l-mgenplus-1c-bold.ttf</font>
      <font>C:\WINDOWS\Fonts\rounded-l-mgenplus-1c-heavy.ttf</font>
      <font>C:\WINDOWS\Fonts\rounded-l-mgenplus-1c-light.ttf</font>
      <font>C:\WINDOWS\Fonts\rounded-l-mgenplus-1c-medium.ttf</font>
      <font>C:\WINDOWS\Fonts\rounded-l-mgenplus-1c-regular.ttf</font>
      <font>C:\WINDOWS\Fonts\rounded-l-mgenplus-1c-thin.ttf</font>
      <font>C:\WINDOWS\Fonts\rounded-l-mgenplus-1cp-black.ttf</font>
      <font>C:\WINDOWS\Fonts\rounded-l-mgenplus-1cp-bold.ttf</font>
      <font>C:\WINDOWS\Fonts\rounded-l-mgenplus-1cp-heavy.ttf</font>
      <font>C:\WINDOWS\Fonts\rounded-l-mgenplus-1cp-light.ttf</font>
      <font>C:\WINDOWS\Fonts\rounded-l-mgenplus-1cp-medium.ttf</font>
      <font>C:\WINDOWS\Fonts\rounded-l-mgenplus-1cp-regular.ttf</font>
      <font>C:\WINDOWS\Fonts\rounded-l-mgenplus-1cp-thin.ttf</font>
      <font>C:\WINDOWS\Fonts\rounded-l-mgenplus-1m-bold.ttf</font>
      <font>C:\WINDOWS\Fonts\rounded-l-mgenplus-1m-light.ttf</font>
      <font>C:\WINDOWS\Fonts\rounded-l-mgenplus-1m-medium.ttf</font>
      <font>C:\WINDOWS\Fonts\rounded-l-mgenplus-1m-regular.ttf</font>
      <font>C:\WINDOWS\Fonts\rounded-l-mgenplus-1m-thin.ttf</font>
      <font>C:\WINDOWS\Fonts\rounded-l-mgenplus-1mn-bold.ttf</font>
      <font>C:\WINDOWS\Fonts\rounded-l-mgenplus-1mn-light.ttf</font>
      <font>C:\WINDOWS\Fonts\rounded-l-mgenplus-1mn-medium.ttf</font>
      <font>C:\WINDOWS\Fonts\rounded-l-mgenplus-1mn-regular.ttf</font>
      <font>C:\WINDOWS\Fonts\rounded-l-mgenplus-1mn-thin.ttf</font>
      <font>C:\WINDOWS\Fonts\rounded-l-mgenplus-1p-black.ttf</font>
      <font>C:\WINDOWS\Fonts\rounded-l-mgenplus-1p-bold.ttf</font>
      <font>C:\WINDOWS\Fonts\rounded-l-mgenplus-1p-heavy.ttf</font>
      <font>C:\WINDOWS\Fonts\rounded-l-mgenplus-1p-light.ttf</font>
      <font>C:\WINDOWS\Fonts\rounded-l-mgenplus-1p-medium.ttf</font>
      <font>C:\WINDOWS\Fonts\rounded-l-mgenplus-1p-regular.ttf</font>
      <font>C:\WINDOWS\Fonts\rounded-l-mgenplus-1p-thin.ttf</font>
      <font>C:\WINDOWS\Fonts\rounded-l-mgenplus-1pp-black.ttf</font>
      <font>C:\WINDOWS\Fonts\rounded-l-mgenplus-1pp-bold.ttf</font>
      <font>C:\WINDOWS\Fonts\rounded-l-mgenplus-1pp-heavy.ttf</font>
      <font>C:\WINDOWS\Fonts\rounded-l-mgenplus-1pp-light.ttf</font>
      <font>C:\WINDOWS\Fonts\rounded-l-mgenplus-1pp-medium.ttf</font>
      <font>C:\WINDOWS\Fonts\rounded-l-mgenplus-1pp-regular.ttf</font>
      <font>C:\WINDOWS\Fonts\rounded-l-mgenplus-1pp-thin.ttf</font>
      <font>C:\WINDOWS\Fonts\rounded-l-mgenplus-2c-black.ttf</font>
      <font>C:\WINDOWS\Fonts\rounded-l-mgenplus-2c-bold.ttf</font>
      <font>C:\WINDOWS\Fonts\rounded-l-mgenplus-2c-heavy.ttf</font>
      <font>C:\WINDOWS\Fonts\rounded-l-mgenplus-2c-light.ttf</font>
      <font>C:\WINDOWS\Fonts\rounded-l-mgenplus-2c-medium.ttf</font>
      <font>C:\WINDOWS\Fonts\rounded-l-mgenplus-2c-regular.ttf</font>
      <font>C:\WINDOWS\Fonts\rounded-l-mgenplus-2c-thin.ttf</font>
      <font>C:\WINDOWS\Fonts\rounded-l-mgenplus-2cp-black.ttf</font>
      <font>C:\WINDOWS\Fonts\rounded-l-mgenplus-2cp-bold.ttf</font>
      <font>C:\WINDOWS\Fonts\rounded-l-mgenplus-2cp-heavy.ttf</font>
      <font>C:\WINDOWS\Fonts\rounded-l-mgenplus-2cp-light.ttf</font>
      <font>C:\WINDOWS\Fonts\rounded-l-mgenplus-2cp-medium.ttf</font>
      <font>C:\WINDOWS\Fonts\rounded-l-mgenplus-2cp-regular.ttf</font>
      <font>C:\WINDOWS\Fonts\rounded-l-mgenplus-2cp-thin.ttf</font>
      <font>C:\WINDOWS\Fonts\rounded-l-mgenplus-2m-bold.ttf</font>
      <font>C:\WINDOWS\Fonts\rounded-l-mgenplus-2m-light.ttf</font>
      <font>C:\WINDOWS\Fonts\rounded-l-mgenplus-2m-medium.ttf</font>
      <font>C:\WINDOWS\Fonts\rounded-l-mgenplus-2m-regular.ttf</font>
      <font>C:\WINDOWS\Fonts\rounded-l-mgenplus-2m-thin.ttf</font>
      <font>C:\WINDOWS\Fonts\rounded-l-mgenplus-2p-black.ttf</font>
      <font>C:\WINDOWS\Fonts\rounded-l-mgenplus-2p-bold.ttf</font>
      <font>C:\WINDOWS\Fonts\rounded-l-mgenplus-2p-heavy.ttf</font>
      <font>C:\WINDOWS\Fonts\rounded-l-mgenplus-2p-light.ttf</font>
      <font>C:\WINDOWS\Fonts\rounded-l-mgenplus-2p-medium.ttf</font>
      <font>C:\WINDOWS\Fonts\rounded-l-mgenplus-2p-regular.ttf</font>
      <font>C:\WINDOWS\Fonts\rounded-l-mgenplus-2p-thin.ttf</font>
      <font>C:\WINDOWS\Fonts\rounded-l-mgenplus-2pp-black.ttf</font>
      <font>C:\WINDOWS\Fonts\rounded-l-mgenplus-2pp-bold.ttf</font>
      <font>C:\WINDOWS\Fonts\rounded-l-mgenplus-2pp-heavy.ttf</font>
      <font>C:\WINDOWS\Fonts\rounded-l-mgenplus-2pp-light.ttf</font>
      <font>C:\WINDOWS\Fonts\rounded-l-mgenplus-2pp-medium.ttf</font>
      <font>C:\WINDOWS\Fonts\rounded-l-mgenplus-2pp-regular.ttf</font>
      <font>C:\WINDOWS\Fonts\rounded-x-mgenplus-1c-black.ttf</font>
      <font>C:\WINDOWS\Fonts\rounded-x-mgenplus-1c-bold.ttf</font>
      <font>C:\WINDOWS\Fonts\rounded-x-mgenplus-1c-heavy.ttf</font>
      <font>C:\WINDOWS\Fonts\rounded-x-mgenplus-1c-light.ttf</font>
      <font>C:\WINDOWS\Fonts\rounded-x-mgenplus-1c-medium.ttf</font>
      <font>C:\WINDOWS\Fonts\rounded-x-mgenplus-1c-regular.ttf</font>
      <font>C:\WINDOWS\Fonts\rounded-x-mgenplus-1c-thin.ttf</font>
      <font>C:\WINDOWS\Fonts\rounded-x-mgenplus-1cp-black.ttf</font>
      <font>C:\WINDOWS\Fonts\rounded-x-mgenplus-1cp-bold.ttf</font>
      <font>C:\WINDOWS\Fonts\rounded-x-mgenplus-1cp-heavy.ttf</font>
      <font>C:\WINDOWS\Fonts\rounded-x-mgenplus-1cp-light.ttf</font>
      <font>C:\WINDOWS\Fonts\rounded-x-mgenplus-1cp-medium.ttf</font>
      <font>C:\WINDOWS\Fonts\rounded-x-mgenplus-1cp-regular.ttf</font>
      <font>C:\WINDOWS\Fonts\rounded-x-mgenplus-1cp-thin.ttf</font>
      <font>C:\WINDOWS\Fonts\rounded-x-mgenplus-1m-bold.ttf</font>
      <font>C:\WINDOWS\Fonts\rounded-x-mgenplus-1m-light.ttf</font>
      <font>C:\WINDOWS\Fonts\rounded-x-mgenplus-1m-medium.ttf</font>
      <font>C:\WINDOWS\Fonts\rounded-x-mgenplus-1m-regular.ttf</font>
      <font>C:\WINDOWS\Fonts\rounded-x-mgenplus-1m-thin.ttf</font>
      <font>C:\WINDOWS\Fonts\rounded-x-mgenplus-1mn-bold.ttf</font>
      <font>C:\WINDOWS\Fonts\rounded-x-mgenplus-1mn-light.ttf</font>
      <font>C:\WINDOWS\Fonts\rounded-x-mgenplus-1mn-medium.ttf</font>
      <font>C:\WINDOWS\Fonts\rounded-x-mgenplus-1mn-regular.ttf</font>
      <font>C:\WINDOWS\Fonts\rounded-x-mgenplus-1mn-thin.ttf</font>
      <font>C:\WINDOWS\Fonts\rounded-x-mgenplus-1p-black.ttf</font>
      <font>C:\WINDOWS\Fonts\rounded-x-mgenplus-1p-bold.ttf</font>
      <font>C:\WINDOWS\Fonts\rounded-x-mgenplus-1p-heavy.ttf</font>
      <font>C:\WINDOWS\Fonts\rounded-x-mgenplus-1p-light.ttf</font>
      <font>C:\WINDOWS\Fonts\rounded-x-mgenplus-1p-medium.ttf</font>
      <font>C:\WINDOWS\Fonts\rounded-x-mgenplus-1p-regular.ttf</font>
      <font>C:\WINDOWS\Fonts\rounded-x-mgenplus-1p-thin.ttf</font>
      <font>C:\WINDOWS\Fonts\rounded-x-mgenplus-1pp-black.ttf</font>
      <font>C:\WINDOWS\Fonts\rounded-x-mgenplus-1pp-bold.ttf</font>
      <font>C:\WINDOWS\Fonts\rounded-x-mgenplus-1pp-heavy.ttf</font>
      <font>C:\WINDOWS\Fonts\rounded-x-mgenplus-1pp-light.ttf</font>
      <font>C:\WINDOWS\Fonts\rounded-x-mgenplus-1pp-medium.ttf</font>
      <font>C:\WINDOWS\Fonts\rounded-x-mgenplus-1pp-regular.ttf</font>
      <font>C:\WINDOWS\Fonts\rounded-x-mgenplus-1pp-thin.ttf</font>
      <font>C:\WINDOWS\Fonts\rounded-x-mgenplus-2c-black.ttf</font>
      <font>C:\WINDOWS\Fonts\rounded-x-mgenplus-2c-bold.ttf</font>
      <font>C:\WINDOWS\Fonts\rounded-x-mgenplus-2c-heavy.ttf</font>
      <font>C:\WINDOWS\Fonts\rounded-x-mgenplus-2c-light.ttf</font>
      <font>C:\WINDOWS\Fonts\rounded-x-mgenplus-2c-medium.ttf</font>
      <font>C:\WINDOWS\Fonts\rounded-x-mgenplus-2c-regular.ttf</font>
      <font>C:\WINDOWS\Fonts\rounded-x-mgenplus-2c-thin.ttf</font>
      <font>C:\WINDOWS\Fonts\rounded-x-mgenplus-2cp-black.ttf</font>
      <font>C:\WINDOWS\Fonts\rounded-x-mgenplus-2cp-bold.ttf</font>
      <font>C:\WINDOWS\Fonts\rounded-x-mgenplus-2cp-heavy.ttf</font>
      <font>C:\WINDOWS\Fonts\rounded-x-mgenplus-2cp-light.ttf</font>
      <font>C:\WINDOWS\Fonts\rounded-x-mgenplus-2cp-medium.ttf</font>
      <font>C:\WINDOWS\Fonts\rounded-x-mgenplus-2cp-regular.ttf</font>
      <font>C:\WINDOWS\Fonts\rounded-x-mgenplus-2cp-thin.ttf</font>
      <font>C:\WINDOWS\Fonts\rounded-x-mgenplus-2m-bold.ttf</font>
      <font>C:\WINDOWS\Fonts\rounded-x-mgenplus-2m-light.ttf</font>
      <font>C:\WINDOWS\Fonts\rounded-x-mgenplus-2m-medium.ttf</font>
      <font>C:\WINDOWS\Fonts\rounded-x-mgenplus-2m-regular.ttf</font>
      <font>C:\WINDOWS\Fonts\rounded-x-mgenplus-2m-thin.ttf</font>
      <font>C:\WINDOWS\Fonts\rounded-x-mgenplus-2p-black.ttf</font>
      <font>C:\WINDOWS\Fonts\rounded-x-mgenplus-2p-bold.ttf</font>
      <font>C:\WINDOWS\Fonts\rounded-x-mgenplus-2p-heavy.ttf</font>
      <font>C:\WINDOWS\Fonts\rounded-x-mgenplus-2p-light.ttf</font>
      <font>C:\WINDOWS\Fonts\rounded-x-mgenplus-2p-medium.ttf</font>
      <font>C:\WINDOWS\Fonts\rounded-x-mgenplus-2p-regular.ttf</font>
      <font>C:\WINDOWS\Fonts\rounded-x-mgenplus-2p-thin.ttf</font>
      <font>C:\WINDOWS\Fonts\rounded-x-mgenplus-2pp-black.ttf</font>
      <font>C:\WINDOWS\Fonts\rounded-x-mgenplus-2pp-bold.ttf</font>
      <font>C:\WINDOWS\Fonts\rounded-x-mgenplus-2pp-heavy.ttf</font>
      <font>C:\WINDOWS\Fonts\rounded-x-mgenplus-2pp-light.ttf</font>
      <font>C:\WINDOWS\Fonts\rounded-x-mgenplus-2pp-medium.ttf</font>
      <font>C:\WINDOWS\Fonts\rounded-x-mgenplus-2pp-regular.ttf</font>
      <font>C:\WINDOWS\Fonts\rounded-x-mgenplus-2pp-thin.ttf</font>
      <font>C:\WINDOWS\Fonts\segmdl2.ttf</font>
      <font>C:\WINDOWS\Fonts\segoepr.ttf</font>
      <font>C:\WINDOWS\Fonts\segoeprb.ttf</font>
      <font>C:\WINDOWS\Fonts\segoesc.ttf</font>
      <font>C:\WINDOWS\Fonts\segoescb.ttf</font>
      <font>C:\WINDOWS\Fonts\segoeui.ttf</font>
      <font>C:\WINDOWS\Fonts\seguibl.ttf</font>
      <font>C:\WINDOWS\Fonts\seguibli.ttf</font>
      <font>C:\WINDOWS\Fonts\segoeuib.ttf</font>
      <font>C:\WINDOWS\Fonts\segoeuiz.ttf</font>
      <font>C:\WINDOWS\Fonts\seguiemj.ttf</font>
      <font>C:\WINDOWS\Fonts\seguihis.ttf</font>
      <font>C:\WINDOWS\Fonts\segoeuii.ttf</font>
      <font>C:\WINDOWS\Fonts\segoeuil.ttf</font>
      <font>C:\WINDOWS\Fonts\seguili.ttf</font>
      <font>C:\WINDOWS\Fonts\seguisb.ttf</font>
      <font>C:\WINDOWS\Fonts\seguisbi.ttf</font>
      <font>C:\WINDOWS\Fonts\segoeuisl.ttf</font>
      <font>C:\WINDOWS\Fonts\seguisli.ttf</font>
      <font>C:\WINDOWS\Fonts\seguisym.ttf</font>
      <font>C:\WINDOWS\Fonts\SF-Ribbon.ttf</font>
      <font>C:\WINDOWS\Fonts\SF-Sweets.ttf</font>
      <font>C:\WINDOWS\Fonts\SF-WebIcon.ttf</font>
      <font>C:\WINDOWS\Fonts\simsunb.ttf</font>
      <font>C:\WINDOWS\Fonts\Sitka.ttc</font>
      <font>C:\WINDOWS\Fonts\SitkaB.ttc</font>
      <font>C:\WINDOWS\Fonts\SitkaZ.ttc</font>
      <font>C:\WINDOWS\Fonts\SitkaI.ttc</font>
      <font>C:\WINDOWS\Fonts\SourceCodePro-Regular.ttf</font>
      <font>C:\WINDOWS\Fonts\SourceCodePro-Black.ttf</font>
      <font>C:\WINDOWS\Fonts\SourceCodePro-Bold.ttf</font>
      <font>C:\WINDOWS\Fonts\SourceCodePro-ExtraLight.ttf</font>
      <font>C:\WINDOWS\Fonts\SourceCodePro-Light.ttf</font>
      <font>C:\WINDOWS\Fonts\SourceCodePro-Semibold.ttf</font>
      <font>C:\WINDOWS\Fonts\sylfaen.ttf</font>
      <font>C:\WINDOWS\Fonts\symbol.ttf</font>
      <font>C:\WINDOWS\Fonts\tahoma.ttf</font>
      <font>C:\WINDOWS\Fonts\tahomabd.ttf</font>
      <font>C:\WINDOWS\Fonts\times.ttf</font>
      <font>C:\WINDOWS\Fonts\timesbd.ttf</font>
      <font>C:\WINDOWS\Fonts\timesbi.ttf</font>
      <font>C:\WINDOWS\Fonts\timesi.ttf</font>
      <font>C:\WINDOWS\Fonts\trebuc.ttf</font>
      <font>C:\WINDOWS\Fonts\trebucbd.ttf</font>
      <font>C:\WINDOWS\Fonts\trebucbi.ttf</font>
      <font>C:\WINDOWS\Fonts\trebucit.ttf</font>
      <font>C:\WINDOWS\Fonts\verdana.ttf</font>
      <font>C:\WINDOWS\Fonts\verdanab.ttf</font>
      <font>C:\WINDOWS\Fonts\verdanaz.ttf</font>
      <font>C:\WINDOWS\Fonts\verdanai.ttf</font>
      <font>C:\WINDOWS\Fonts\WaonJoyo-R.otf</font>
      <font>C:\WINDOWS\Fonts\webdings.ttf</font>
      <font>C:\WINDOWS\Fonts\wingding.ttf</font>
      <font>C:\WINDOWS\Fonts\YasashisaBold.otf</font>
      <font>C:\WINDOWS\Fonts\YuGothB.ttc</font>
      <font>C:\WINDOWS\Fonts\YuGothL.ttc</font>
      <font>C:\WINDOWS\Fonts\YuGothM.ttc</font>
      <font>C:\WINDOWS\Fonts\YuGothR.ttc</font>
      <font>C:\WINDOWS\Fonts\えみんこフォント.ttf</font>
      <font>C:\WINDOWS\Fonts\えれがんとW3-清音.TTF</font>
      <font>C:\WINDOWS\Fonts\えれがんとW5-清音.TTF</font>
      <font>C:\WINDOWS\Fonts\えれがんとW7-清音.TTF</font>
      <font>C:\WINDOWS\Fonts\えれがんとW9-清音.TTF</font>
      <font>C:\WINDOWS\Fonts\Kokoro.otf</font>
      <font>C:\WINDOWS\Fonts\セプテンバーＬ教漢.TTF</font>
      <font>C:\WINDOWS\Fonts\セプテンバーＬ-等幅教漢.TTF</font>
      <font>C:\WINDOWS\Fonts\セプテンバーＭ教漢.TTF</font>
      <font>C:\WINDOWS\Fonts\セプテンバーＭ-等幅教漢.TTF</font>
      <font>C:\WINDOWS\Fonts\ダーツフォント.ttf</font>
      <font>C:\WINDOWS\Fonts\タロ子フォント.ttf</font>
      <font>C:\WINDOWS\Fonts\はなぞめフォント.ttf</font>
      <font>C:\WINDOWS\Fonts\Hannari.otf</font>
      <font>C:\WINDOWS\Fonts\Pigmo-00.otf</font>
      <font>C:\WINDOWS\Fonts\Pigmo-01.otf</font>
      <font>C:\WINDOWS\Fonts\Planetarium.otf</font>
      <font>C:\WINDOWS\Fonts\font_1_honokamarugo_1.1.ttf</font>
      <font>C:\WINDOWS\Fonts\Makinas-Scrap-5.otf</font>
      <font>C:\WINDOWS\Fonts\mamemoji.ttf</font>
      <font>C:\WINDOWS\Fonts\Mutsuki.ttf</font>
      <font>C:\WINDOWS\Fonts\yurumoji.ttf</font>
      <font>C:\WINDOWS\Fonts\yomogifont.otf</font>
      <font>C:\WINDOWS\Fonts\RiiT.otf</font>
      <font>C:\WINDOWS\Fonts\font_1_kokugl_1.15_rls.ttf</font>
      <font>C:\WINDOWS\Fonts\KUDOU.TTF</font>
      <font>C:\WINDOWS\Fonts\sp-setofont.ttf</font>
      <font>C:\WINDOWS\Fonts\SeigoKanaClassicTrial-ExtraLight.otf</font>
      <font>C:\WINDOWS\Fonts\SeiminKanaClassicTrial-ExtraLight.otf</font>
      <font>C:\WINDOWS\Fonts\chogokubosogothic.ttf</font>
    </set>
  </sets>
</library>
